<?xml version="1.0" encoding="UTF-8" standalone="yes"?>
<ns2:rssItem uri="6cdf3e0e-3db2-4228-b4ba-e67914fbae7c" xmlns:ns2="ims.health.entities">
    <category>كرة مصرية</category>
    <comments>https://sport.aljazeera.net/football/egypt/2019/4/18/محمد-صلاح-التايم-حوار-المرأة-الرجال-مصر-العالم-الإسلامي</comments>
    <description>حث النجم المصري محمد صلاح مهاجم ليفربول الإنجليزي لكرة القدم الرجال في مصر والعالم الإسلامي على إبداء مزيد من الاحترام للمرأة، وقال إن عليهم أن يغيروا طريقة معاملتهم لها، وذلك في مناسبة يدلي فيها برأيه في مسألة المساواة بين الجنسين.</description>
    <link>https://sport.aljazeera.net/football/egypt/2019/4/18/محمد-صلاح-التايم-حوار-المرأة-الرجال-مصر-العالم-الإسلامي</link>
    <pubDate>2019-04-18T11:14:48+03:00</pubDate>
    <title>صلاح يدعو لتعزيز احترام المرأة بمصر والعالم الإسلامي</title>
</ns2:rssItem>

