<?xml version="1.0" encoding="UTF-8" standalone="yes"?>
<ns2:rssItem uri="c291437d-2759-4ebf-bdfb-200a516c048e" xmlns:ns2="ims.health.entities">
    <category>سياسة</category>
    <comments>https://www.aljazeera.net/news/politics/2019/4/20/استشهاد-شاب-فلسطيني</comments>
    <description>استشهد شاب فلسطيني اليوم السبت متأثرا بجروح أصيب بها عندما أطلق عليه جنود الاحتلال النار عند حاجز زعترة جنوب نابلس بالضفة الغربية.</description>
    <link>https://www.aljazeera.net/news/politics/2019/4/20/استشهاد-شاب-فلسطيني</link>
    <pubDate>2019-04-20T19:18:45+03:00</pubDate>
    <title>شاب فلسطيني يلتحق بموكب الشهداء</title>
</ns2:rssItem>

