<?xml version="1.0" encoding="UTF-8" standalone="yes"?>
<ns2:rssItem uri="2b00e3da-4c94-415f-b61c-0607a7eaa72c" xmlns:ns2="ims.health.entities">
    <category>سياسة</category>
    <comments>https://www.aljazeera.net/news/politics/2019/4/19/المجلس-الرئاسي-خلاف-مكتوم-السودان</comments>
    <description>يعتقد محللون وزعماء في المعارضة السودانية أن سبب تأخر المجلس العسكري الانتقالي في الرد على مطالب قوى التغيير التي تسلمها مؤخرا يعود إلى تشبثه بالهيمنة على تشكيلة المجلس الرئاسي.</description>
    <link>https://www.aljazeera.net/news/politics/2019/4/19/المجلس-الرئاسي-خلاف-مكتوم-السودان</link>
    <pubDate>2019-04-19T10:39:03+03:00</pubDate>
    <title>المجلس الرئاسي.. سر الخلاف المكتوم بين العسكر والمعارضة بالسودان</title>
</ns2:rssItem>

